drun_airsim_client/__init__.py
drun_airsim_client-0.0.3.dist-info/METADATA
drun_airsim_client-0.0.3.dist-info/WHEEL
drun_airsim_client-0.0.3.dist-info/top_level.txt
drun_airsim_client-0.0.3.dist-info/RECORD
